dbt/__init__.py
dbt/adapters/__init__.py
dbt/adapters/exasol/__init__.py
dbt/adapters/exasol/__version__.py
dbt/adapters/exasol/column.py
dbt/adapters/exasol/connections.py
dbt/adapters/exasol/impl.py
dbt/adapters/exasol/relation.py
dbt/include/__init__.py
dbt/include/exasol/__init__.py
dbt/include/exasol/dbt_project.yml
dbt/include/exasol/macros/adapters.sql
dbt/include/exasol/macros/apply_grants.sql
dbt/include/exasol/macros/catalog.sql
dbt/include/exasol/macros/create_table_helpers.sql
dbt/include/exasol/macros/materializations/incremental.sql
dbt/include/exasol/macros/materializations/incremental_strategies.sql
dbt/include/exasol/macros/materializations/merge.sql
dbt/include/exasol/macros/materializations/seed.sql
dbt/include/exasol/macros/materializations/snapshot.sql
dbt/include/exasol/macros/materializations/snapshot_merge.sql
dbt/include/exasol/macros/materializations/strategies.sql
dbt/include/exasol/macros/materializations/tests/helpers.sql
dbt/include/exasol/macros/metadata.sql
dbt/include/exasol/macros/utils/any_value.sql
dbt/include/exasol/macros/utils/bool_or.sql
dbt/include/exasol/macros/utils/dateadd.sql
dbt/include/exasol/macros/utils/datediff.sql
dbt/include/exasol/macros/utils/hash.sql
dbt/include/exasol/macros/utils/last_day.sql
dbt/include/exasol/macros/utils/listagg.sql
dbt/include/exasol/macros/utils/safe_cast.sql
dbt/include/exasol/macros/utils/split_part.sql
dbt/include/exasol/macros/utils/timestamps.sql
dbt/include/exasol/macros/validate_sql.sql
dbt/include/exasol/profile_template.yml
dbt_exasol-1.10.0.dist-info/WHEEL
dbt_exasol-1.10.0.dist-info/METADATA
dbt_exasol-1.10.0.dist-info/RECORD
