Metadata-Version: 2.3
Name: dbt-exasol
Version: 1.10.0
Summary: Adapter to dbt-core for warehouse Exasol
Author: Torsten Glunde, Ilija Kutle
Author-email: Torsten Glunde <torsten.glunde@alligator-company.com>, Ilija Kutle <ilija.kutle@alligator-company.com>
License: GPL-3.0-or-later
Requires-Dist: pyexasol>=1.0.0
Requires-Dist: sqlfluff>=2.3,<4.0
Requires-Dist: pyyaml==6.0.1
Requires-Dist: pytest-xdist>=3.3.1
Requires-Dist: protobuf>=5.0,<7.0
Requires-Dist: dbt-adapters>=1.10.0
Requires-Dist: dbt-core>=1.10.0
Requires-Dist: dbt-tests-adapter>=1.10.0
Requires-Dist: python-dotenv>=1.2.1
Requires-Dist: tox>=4.30.3
Requires-Dist: ruff>=0.14.8
Requires-Dist: pylint>=2.15.8 ; extra == 'dev'
Requires-Dist: exceptiongroup>=1.1.1 ; extra == 'dev'
Requires-Dist: black>=22.8,<25.0 ; extra == 'dev'
Requires-Dist: pytest>=7.2.0 ; extra == 'dev'
Requires-Dist: pytest-dotenv>=0.5.2 ; extra == 'dev'
Requires-Dist: tox>=3.26.0 ; extra == 'dev'
Requires-Dist: pytest-parallel>=0.1.1 ; extra == 'dev'
Requires-Dist: ipykernel>=6.25.0 ; extra == 'dev'
Requires-Dist: pytest-xdist>=3.3.1 ; extra == 'dev'
Requires-Python: >=3.9.2, <3.13
Project-URL: Homepage, https://alligatorcompany.gitlab.io/dbt-exasol
Project-URL: Repository, https://github.com/tglunde/dbt-exasol
Provides-Extra: dev
